[{"id":1,"kategorija":"Graficke Kartice","cena":"36990","tekstOglasa":"GTX 1660 super 6gb"},{"id":2,"kategorija":"Procesori","cena":"29990","tekstOglasa":"AMD Ryzen 5 3600X"},{"id":3,"kategorija":"Procesori","cena":23590,"tekstOglasa":"Intel i5 10400"},{"id":4,"kategorija":"Graficke Kartice","cena":30000,"tekstOglasa":"GTX 1660ti"},{"id":5,"kategorija":"Maticne Ploce","cena":"14000","tekstOglasa":"B450 TOMAHAWK MAX"},{"id":6,"kategorija":"Graficke Kartice","cena":"24990","tekstOglasa":"GTX 1650s"},{"id":7,"kategorija":"Procesori","cena":"60500","tekstOglasa":"Intel i9 10900k"},{"id":8,"kategorija":"Procesori","cena":"29000","tekstOglasa":"Ryzen 5 3600"},{"id":9,"kategorija":"Maticne Ploce","cena":"19000","tekstOglasa":"X570 Phantom"},{"id":10,"kategorija":"Graficke Kartice","cena":"11000","tekstOglasa":"GT 1030"},{"id":11,"kategorija":"Maticne Ploce","cena":"16000","tekstOglasa":"Z390 D"},{"id":12,"kategorija":"Maticne Ploce","cena":"8000","tekstOglasa":"B365M H"},{"id":13,"kategorija":"Procesori","cena":"42000","tekstOglasa":"Ryzen 7 3700X"},{"id":14,"kategorija":"Procesori","cena":"100000","tekstOglasa":"Ryzen 9 3950x"},{"id":15,"kategorija":"Graficke Kartice","cena":"90000","tekstOglasa":"RTX 2060"},{"id":16,"kategorija":"Maticne Ploce","cena":"21000","tekstOglasa":"B560 "},{"id":17,"kategorija":"Maticne Ploce","cena":"8000","tekstOglasa":"D1800M"},{"id":18,"kategorija":"Graficke Kartice","cena":"7000","tekstOglasa":"GT 710"},{"id":19,"kategorija":"Graficke Kartice","cena":"22000","tekstOglasa":"RX 550"},{"id":20,"kategorija":"Procesori","cena":"52000","tekstOglasa":"Ryzen 7 3800XT"},{"id":21,"kategorija":"Procesori","cena":"10000","tekstOglasa":"Ryzen 3 1200"},{"id":22,"kategorija":"Maticne Ploce","cena":"7500","tekstOglasa":"A320M-S2H"}]